versionfinder/__init__.py
versionfinder/version.py
versionfinder/versionfinder.py
versionfinder/versioninfo.py
versionfinder/tests/__init__.py
versionfinder/tests/test_acceptance.py
versionfinder/tests/test_init.py
versionfinder/tests/test_version.py
versionfinder/tests/test_versionfinder.py
versionfinder/tests/test_versioninfo.py
versionfinder-1.1.1.dist-info/LICENSE
versionfinder-1.1.1.dist-info/METADATA
versionfinder-1.1.1.dist-info/WHEEL
versionfinder-1.1.1.dist-info/top_level.txt
versionfinder-1.1.1.dist-info/RECORD
