Metadata-Version: 1.1
Name: versionfinder
Version: 1.1.1
Summary: Python package to find the version of another package, whether installed via pip, setuptools or git.
Home-page: https://github.com/jantman/versionfinder
Author: Jason Antman
Author-email: jason@jasonantman.com
License: UNKNOWN
Keywords: version git pip pkg_resources setuptools
Platform: UNKNOWN
Classifier: Development Status :: 5 - Production/Stable
Classifier: Intended Audience :: Developers
Classifier: License :: OSI Approved :: GNU Lesser General Public License v3 (LGPLv3)
Classifier: Operating System :: OS Independent
Classifier: Programming Language :: Python
Classifier: Programming Language :: Python :: 3
Classifier: Topic :: Software Development
Classifier: Topic :: Software Development :: Libraries
Classifier: Topic :: Software Development :: Version Control
